blastMining/__init__.py
blastMining/blastMining.py
blastMining/besthit/__init__.py
blastMining/besthit/besthit.py
blastMining/full_pipeline/__init__.py
blastMining/full_pipeline/full_pipeline.py
blastMining/lca/__init__.py
blastMining/lca/lca.py
blastMining/script/__init__.py
blastMining/script/besthit_script.py
blastMining/script/create_dir.py
blastMining/script/get_taxid.py
blastMining/script/lca_script.py
blastMining/script/read_multidfs.py
blastMining/script/run_besthit.py
blastMining/script/run_lca.py
blastMining/script/run_vote.py
blastMining/script/run_voteSpecies.py
blastMining/script/splitdf2list.py
blastMining/script/summary2krona.py
blastMining/script/summary_df.py
blastMining/script/tab2krona.py
blastMining/script/voteSpecies_script.py
blastMining/script/vote_script.py
blastMining/vote/__init__.py
blastMining/vote/vote.py
blastMining/voteSpecies/__init__.py
blastMining/voteSpecies/voteSpecies.py
blastMining-1.2.0.data/scripts/blastMining_lca.sh
blastMining-1.2.0.data/scripts/blastMining_lca2.sh
blastMining-1.2.0.data/scripts/run_besthit.py
blastMining-1.2.0.data/scripts/run_lca.py
blastMining-1.2.0.data/scripts/run_vote.py
blastMining-1.2.0.data/scripts/run_voteSpecies.py
blastMining-1.2.0.data/scripts/tab2krona.py
blastMining-1.2.0.dist-info/LICENSE
blastMining-1.2.0.dist-info/METADATA
blastMining-1.2.0.dist-info/WHEEL
blastMining-1.2.0.dist-info/entry_points.txt
blastMining-1.2.0.dist-info/top_level.txt
blastMining-1.2.0.dist-info/RECORD
